sqlsimple/__init__.py
sqlsimple/main.py
sqlsimple-0.dist-info/LICENSE
sqlsimple-0.dist-info/WHEEL
sqlsimple-0.dist-info/METADATA
sqlsimple-0.dist-info/RECORD
